<!--suppress XmlUnboundNsPrefix -->
<wizard>
    <step id="welcome">
        <text value="Welcome to the restore wizard.\n\nA backup has been detected.\nYou can use this wizard to restore your settings and any extra plugins that were installed when the backup was created.\n"/>
        <displaytext value="A backup has been detected."/>
        <list type="dynamic" source="listAction" evaluation="ActionSelectionMade" onselect="ActionSelectionMoved"/>
        <code>
self.clearSelectedKeys()
self.selectKey("OK")
        </code>
        <code pos="after" async="yes">
self.buildList(self.selectedAction)
        </code>
    </step>

    <step id="settingsquestion">
        <text value="Do you want to restore your Enigma2 settings ?"/>
        <displaytext value="Do you want to restore your Enigma2 settings ?"/>
        <list type="dynamic" source="listAction2" evaluation="ActionSelectionMade" onselect="ActionSelectionMoved"/>
        <code>
self.clearSelectedKeys()
self.selectKey("OK")
        </code>
        <code pos="after" async="yes">
self.buildList(self.selectedAction)
        </code>
    </step>

    <step id="settingsrestore">
        <text value="Please select the file to restore."/>
        <displaytext value="Please select the file to restore."/>
        <list type="dynamic" source="listDevices" evaluation="settingsdeviceSelectionMade" onselect="settingsdeviceSelectionMoved"/>
        <code>
self.clearSelectedKeys()
self.selectKey("OK")
        </code>
        <code pos="after" async="yes">
self.buildList(self.selectedAction)
        </code>
    </step>

    <step id="pluginsquestion">
        <text value="Do you want to restore your Enigma2 plugins ?"/>
        <displaytext value="Do you want to restore your Enigma2 plugins ?"/>
        <list type="dynamic" source="listAction3" evaluation="ActionSelectionMade" onselect="ActionSelectionMoved"/>
        <code>
self.clearSelectedKeys()
self.selectKey("OK")
        </code>
        <code pos="after" async="yes">
self.buildList(self.selectedAction)
        </code>
    </step>

    <step id="pluginsrestoredevice">
        <text value="Please select the file to restore."/>
        <displaytext value="Please select the file to restore."/>
        <list type="dynamic" source="listDevices" evaluation="pluginsdeviceSelectionMade" onselect="pluginsdeviceSelectionMoved"/>
        <code>
self.clearSelectedKeys()
self.selectKey("OK")
        </code>
        <code pos="after" async="yes">
self.buildList(self.selectedAction)
        </code>
    </step>

    <step id="pluginrestore">
        <text value="The wizard is finished now, and will reboot."/>
        <displaytext value="The wizard is finished now, and will reboot."/>
        <code>
self.buildList(None)
        </code>
    </step>

    <step id="reboot">
        <text value="The wizard is finished now, and will reboot."/>
        <displaytext value="The wizard is finished now, and will reboot."/>
        <code>
self.buildList(None)
        </code>
    </step>
    <step id="noplugins">
        <text value="No plugins needed to be installed"/>
        <displaytext value="No plugins needed to be installed"/>
    </step>
    <step id="end">
        <text value="The wizard is finished now."/>
        <displaytext value="The wizard is finished now."/>
    </step>
</wizard>
